{
	"entities": {
		"Base": {
			"accumulator": "AccumulatorRendering",
			"active-provider-chest": "LogisticContainerRendering",
			"arithmetic-combinator": "ArithmeticCombinatorRendering",
			"artillery-turret": "ArtilleryTurretRendering",
			"artillery-wagon": "ArtilleryWagonRendering",
			"assembling-machine-1": "AssemblingMachineRendering",
			"assembling-machine-2": "AssemblingMachineRendering",
			"assembling-machine-3": "AssemblingMachineRendering",
			"beacon": "BeaconRendering",
			"big-electric-pole": "ElectricPoleRendering",
			"boiler": "BoilerRendering",
			"buffer-chest": "LogisticContainerRendering",
			"bulk-inserter": "InserterRendering",
			"burner-generator": "BurnerGeneratorRendering",
			"burner-inserter": "InserterRendering",
			"burner-mining-drill": "MiningDrillRendering",
			"car": "CarRendering",
			"centrifuge": "AssemblingMachineRendering",
			"chemical-plant": "AssemblingMachineRendering",
			"constant-combinator": "ConstantCombinatorRendering",
			"curved-rail-a": "CurvedRailARendering",
			"curved-rail-b": "CurvedRailBRendering",
			"decider-combinator": "DeciderCombinatorRendering",
			"display-panel": "DisplayPanelRendering",
			"electric-energy-interface": "ElectricEnergyInterfaceRendering",
			"electric-furnace": "FurnaceRendering",
			"electric-mining-drill": "MiningDrillRendering",
			"express-loader": "Loader1x2Rendering",
			"express-splitter": "SplitterRendering",
			"express-transport-belt": "TransportBeltRendering",
			"express-underground-belt": "UndergroundBeltRendering",
			"fast-inserter": "InserterRendering",
			"fast-loader": "Loader1x2Rendering",
			"fast-splitter": "SplitterRendering",
			"fast-transport-belt": "TransportBeltRendering",
			"fast-underground-belt": "UndergroundBeltRendering",
			"flamethrower-turret": "FluidTurretRendering",
			"fluid-wagon": "RollingStockRendering",
			"gate": "GateRendering",
			"gun-turret": "AmmoTurretRendering",
			"half-diagonal-rail": "HalfDiagonalRailRendering",
			"heat-exchanger": "BoilerRendering",
			"heat-interface": "HeatInterfaceRendering",
			"heat-pipe": "HeatPipeRendering",
			"infinity-chest": "InfinityContainerRendering",
			"infinity-pipe": "PipeRendering",
			"inserter": "InserterRendering",
			"iron-chest": "BasicContainerRendering",
			"lab": "LabRendering",
			"land-mine": "LandMineRendering",
			"lane-splitter": "LaneSplitterRendering",
			"laser-turret": "ElectricTurretRendering",
			"legacy-curved-rail": "LegacyCurvedRailRendering",
			"legacy-straight-rail": "LegacyStraightRailRendering",
			"linked-belt": "LinkedBeltRendering",
			"linked-chest": "LinkedContainerRendering",
			"loader": "Loader1x2Rendering",
			"loader-1x1": "Loader1x1Rendering",
			"locomotive": "RollingStockRendering",
			"long-handed-inserter": "InserterRendering",
			"medium-electric-pole": "ElectricPoleRendering",
			"nuclear-reactor": "ReactorRendering",
			"offshore-pump": "OffshorePumpRendering",
			"oil-refinery": "AssemblingMachineRendering",
			"passive-provider-chest": "LogisticContainerRendering",
			"pipe": "PipeRendering",
			"pipe-to-ground": "PipeToGroundRendering",
			"power-switch": "PowerSwitchRendering",
			"programmable-speaker": "ProgrammableSpeakerRendering",
			"pump": "PumpRendering",
			"pumpjack": "MiningDrillRendering",
			"radar": "RadarRendering",
			"rail-chain-signal": "RailChainSignalRendering",
			"rail-signal": "RailSignalRendering",
			"requester-chest": "LogisticContainerRendering",
			"roboport": "RoboportRendering",
			"rocket-silo": "RocketSiloRendering",
			"selector-combinator": "SelectorCombinatorRendering",
			"small-electric-pole": "ElectricPoleRendering",
			"small-lamp": "LampRendering",
			"solar-panel": "SolarPanelRendering",
			"spidertron": "SpiderVehicleRendering",
			"splitter": "SplitterRendering",
			"steam-engine": "GeneratorRendering",
			"steam-turbine": "GeneratorRendering",
			"steel-chest": "BasicContainerRendering",
			"steel-furnace": "FurnaceRendering",
			"stone-furnace": "FurnaceRendering",
			"stone-wall": "WallRendering",
			"storage-chest": "LogisticContainerRendering",
			"storage-tank": "StorageTankRendering",
			"straight-rail": "StraightRailRendering",
			"substation": "ElectricPoleRendering",
			"tank": "CarRendering",
			"train-stop": "TrainStopRendering",
			"transport-belt": "TransportBeltRendering",
			"underground-belt": "UndergroundBeltRendering",
			"wooden-chest": "BasicContainerRendering"
		},
		"Space Age": {
			"agricultural-tower": "AgriculturalTowerRendering",
			"asteroid-collector": "AsteroidCollectorRendering",
			"big-mining-drill": "MiningDrillRendering",
			"biochamber": "AssemblingMachineRendering",
			"biolab": "LabRendering",
			"captive-biter-spawner": "AssemblingMachineRendering",
			"cargo-bay": "CargoBayRendering",
			"cargo-landing-pad": "CargoLandingPadRendering",
			"cargo-wagon": "RollingStockRendering",
			"crusher": "AssemblingMachineRendering",
			"cryogenic-plant": "AssemblingMachineRendering",
			"electromagnetic-plant": "AssemblingMachineRendering",
			"elevated-curved-rail-a": "ElevatedCurvedRailARendering",
			"elevated-curved-rail-b": "ElevatedCurvedRailBRendering",
			"elevated-half-diagonal-rail": "ElevatedHalfDiagonalRailRendering",
			"elevated-straight-rail": "ElevatedStraightRailRendering",
			"foundry": "AssemblingMachineRendering",
			"fusion-generator": "FusionGeneratorRendering",
			"fusion-reactor": "FusionReactorRendering",
			"heating-tower": "ReactorRendering",
			"lightning-collector": "LightningAttractorRendering",
			"lightning-rod": "LightningAttractorRendering",
			"rail-ramp": "RailRampRendering",
			"rail-support": "RailSupportRendering",
			"railgun-turret": "AmmoTurretRendering",
			"recycler": "FurnaceRendering",
			"rocket-turret": "AmmoTurretRendering",
			"space-platform-hub": "SpacePlatformHubRendering",
			"stack-inserter": "InserterRendering",
			"tesla-turret": "ElectricTurretRendering",
			"thruster": "ThrusterRendering",
			"turbo-loader": "Loader1x2Rendering",
			"turbo-splitter": "SplitterRendering",
			"turbo-transport-belt": "TransportBeltRendering",
			"turbo-underground-belt": "UndergroundBeltRendering"
		}
	},
	"tiles": {
		"Base": [
			"concrete",
			"hazard-concrete-left",
			"hazard-concrete-right",
			"landfill",
			"refined-concrete",
			"refined-hazard-concrete-left",
			"refined-hazard-concrete-right",
			"stone-path"
		],
		"Space Age": [
			"foundation",
			"ice-platform",
			"artificial-jellynut-soil",
			"overgrowth-jellynut-soil",
			"space-platform-foundation",
			"artificial-yumako-soil",
			"overgrowth-yumako-soil"
		]
	}
}